wechatpy/__init__.py
wechatpy/_compat.py
wechatpy/component.py
wechatpy/constants.py
wechatpy/events.py
wechatpy/exceptions.py
wechatpy/fields.py
wechatpy/messages.py
wechatpy/oauth.py
wechatpy/parser.py
wechatpy/replies.py
wechatpy/utils.py
wechatpy/client/__init__.py
wechatpy/client/base.py
wechatpy/client/api/__init__.py
wechatpy/client/api/base.py
wechatpy/client/api/card.py
wechatpy/client/api/cloud.py
wechatpy/client/api/customservice.py
wechatpy/client/api/datacube.py
wechatpy/client/api/device.py
wechatpy/client/api/group.py
wechatpy/client/api/invoice.py
wechatpy/client/api/jsapi.py
wechatpy/client/api/marketing.py
wechatpy/client/api/material.py
wechatpy/client/api/media.py
wechatpy/client/api/menu.py
wechatpy/client/api/message.py
wechatpy/client/api/misc.py
wechatpy/client/api/poi.py
wechatpy/client/api/qrcode.py
wechatpy/client/api/scan.py
wechatpy/client/api/semantic.py
wechatpy/client/api/shakearound.py
wechatpy/client/api/tag.py
wechatpy/client/api/template.py
wechatpy/client/api/user.py
wechatpy/client/api/wifi.py
wechatpy/client/api/wxa.py
wechatpy/client/api/merchant/__init__.py
wechatpy/client/api/merchant/category.py
wechatpy/client/api/merchant/common.py
wechatpy/client/api/merchant/express.py
wechatpy/client/api/merchant/group.py
wechatpy/client/api/merchant/order.py
wechatpy/client/api/merchant/shelf.py
wechatpy/client/api/merchant/stock.py
wechatpy/crypto/__init__.py
wechatpy/crypto/base.py
wechatpy/crypto/cryptography.py
wechatpy/crypto/pkcs7.py
wechatpy/crypto/pycrypto.py
wechatpy/enterprise/__init__.py
wechatpy/enterprise/crypto.py
wechatpy/enterprise/events.py
wechatpy/enterprise/exceptions.py
wechatpy/enterprise/messages.py
wechatpy/enterprise/parser.py
wechatpy/enterprise/replies.py
wechatpy/enterprise/client/__init__.py
wechatpy/enterprise/client/api/OA.py
wechatpy/enterprise/client/api/__init__.py
wechatpy/enterprise/client/api/agent.py
wechatpy/enterprise/client/api/appchat.py
wechatpy/enterprise/client/api/batch.py
wechatpy-1.8.18.dist-info/LICENSE
wechatpy-1.8.18.dist-info/METADATA
wechatpy-1.8.18.dist-info/WHEEL
wechatpy-1.8.18.dist-info/top_level.txt
wechatpy-1.8.18.dist-info/RECORD
